Metadata-Version: 2.1
Name: training-pipeline-mm
Version: 0.1.0
Summary: 
Author: Iusztin Paul
Author-email: p.e.iusztin@gmail.com
Requires-Python: >=3.9,<3.10
Classifier: Programming Language :: Python :: 3
Classifier: Programming Language :: Python :: 3.9
Requires-Dist: Jinja2 (==3.0.1)
Requires-Dist: fire (>=0.5.0,<0.6.0)
Requires-Dist: hopsworks (==3.4.3)
Requires-Dist: lightgbm (>=3.3.5,<4.0.0)
Requires-Dist: matplotlib (>=3.7.1,<4.0.0)
Requires-Dist: pyarrow (>=11.0.0,<12.0.0)
Requires-Dist: python-dotenv (>=1.0.0,<2.0.0)
Requires-Dist: seaborn (>=0.12.2,<0.13.0)
Requires-Dist: sktime (>=0.16.1,<0.17.0)
Requires-Dist: wandb (>=0.14.0,<0.15.0)
